ilamb3/__init__.py
ilamb3/_version.py
ilamb3/cache.py
ilamb3/compare.py
ilamb3/config.py
ilamb3/dataset.py
ilamb3/exceptions.py
ilamb3/meta.py
ilamb3/parallel.py
ilamb3/plot.py
ilamb3/py.typed
ilamb3/regions.py
ilamb3/run.py
ilamb3/analysis/__init__.py
ilamb3/analysis/accumulate.py
ilamb3/analysis/area.py
ilamb3/analysis/base.py
ilamb3/analysis/bias.py
ilamb3/analysis/cycle.py
ilamb3/analysis/hydro.py
ilamb3/analysis/nbp.py
ilamb3/analysis/quantiles.py
ilamb3/analysis/relationship.py
ilamb3/analysis/rmse.py
ilamb3/analysis/runoff_sensitivity.py
ilamb3/analysis/spatial_distribution.py
ilamb3/analysis/timeseries.py
ilamb3/cli/__init__.py
ilamb3/configure/ilamb.yaml
ilamb3/configure/iomb.yaml
ilamb3/registry/__init__.py
ilamb3/registry/ilamb.txt
ilamb3/registry/ilamb3.txt
ilamb3/registry/iomb.txt
ilamb3/registry/test.txt
ilamb3/templates/__init__.py
ilamb3/templates/dataset_page.html
ilamb3/templates/directory.html
ilamb3/templates/unified_dashboard.html
ilamb3/tests/__init__.py
ilamb3/tests/test_bias.py
ilamb3/tests/test_compare.py
ilamb3/tests/test_config.py
ilamb3/tests/test_dataset.py
ilamb3/tests/test_exceptions.py
ilamb3/tests/test_hydro.py
ilamb3/tests/test_nbp.py
ilamb3/tests/test_plot.py
ilamb3/tests/test_quantiles.py
ilamb3/tests/test_regions.py
ilamb3/tests/test_registry.py
ilamb3/tests/test_relationship.py
ilamb3/tests/test_run.py
ilamb3/tests/test_runoff.py
ilamb3/tests/test_transform.py
ilamb3/transform/__init__.py
ilamb3/transform/amoc.py
ilamb3/transform/base.py
ilamb3/transform/expression.py
ilamb3/transform/gradient.py
ilamb3/transform/integrate.py
ilamb3/transform/ohc.py
ilamb3/transform/permafrost.py
ilamb3/transform/runoff_sensitivity.py
ilamb3/transform/select.py
ilamb3/transform/soilmoisture.py
ilamb3/transform/stratification_index.py
ilamb3-2025.12.12.dist-info/licenses/LICENSE
ilamb3-2025.12.12.dist-info/METADATA
ilamb3-2025.12.12.dist-info/WHEEL
ilamb3-2025.12.12.dist-info/entry_points.txt
ilamb3-2025.12.12.dist-info/top_level.txt
ilamb3-2025.12.12.dist-info/RECORD
