Metadata-Version: 2.4
Name: ilamb3
Version: 2025.12.12
Summary: Earth system model benchmarking
Author-email: Nathan Collier <nathaniel.collier@gmail.com>
License-Expression: BSD-3-Clause
Classifier: Development Status :: 4 - Beta
Classifier: Operating System :: OS Independent
Classifier: Intended Audience :: Science/Research
Classifier: Programming Language :: Python
Classifier: Programming Language :: Python :: 3
Classifier: Programming Language :: Python :: 3.10
Classifier: Programming Language :: Python :: 3.11
Classifier: Programming Language :: Python :: 3.12
Classifier: Programming Language :: Python :: 3.13
Classifier: Topic :: Scientific/Engineering
Requires-Python: >=3.10
License-File: LICENSE
Requires-Dist: cf-xarray>=0.10.0
Requires-Dist: numpy>=2.2.2
Requires-Dist: pandas>=2.2.3
Requires-Dist: pint-xarray>=0.4
Requires-Dist: xarray<=2025.10.1
Requires-Dist: netcdf4>=1.7.2
Requires-Dist: pooch>=1.8.2
Requires-Dist: scipy>=1.15.1
Requires-Dist: matplotlib>=3.10.0
Requires-Dist: cartopy>=0.24.1
Requires-Dist: pyyaml>=6.0.2
Requires-Dist: jinja2>=3.1.5
Requires-Dist: statsmodels>=0.14.4
Requires-Dist: loguru>=0.7.3
Requires-Dist: dask>=2025.2.0
Requires-Dist: nc-time-axis>=1.4.1
Requires-Dist: tqdm>=4.67.1
Requires-Dist: pyarrow>=21.0.0
Requires-Dist: typer>=0.20.0
Dynamic: license-file
